list_overlap/__init__.py
list_overlap/overlaps1.py
tests/__init__.py
tests/overlap_tests.py
vennoverlap-0.1.0.dist-info/LICENSE
vennoverlap-0.1.0.dist-info/METADATA
vennoverlap-0.1.0.dist-info/WHEEL
vennoverlap-0.1.0.dist-info/top_level.txt
vennoverlap-0.1.0.dist-info/RECORD
