Metadata-Version: 2.1
Name: vennoverlap
Version: 0.1.0
Summary: vennoverlap is a package which would help to generate lists of overlaps between columns of given dataframe. eg. If you plot a venn diagram between 2 or more list, it will not provide you the values. But this library will gives you the value
Home-page: https://github.com/ranijames/Data_overlap
Author: Alva Rani James
Author-email: alvarani@gmail.com
License: MIT License
License-File: LICENSE
Requires-Dist: pandas
Requires-Dist: itertools
